{
  "name": "Zen Dense Tabs",
  "id": "zen-dense-tabs",
  "version": "1.0.0",
  "author": "Bischtinius",
  "description": "Tightens tab spacing and workspace indicator height for a denser layout.",
  "tested_on": "Zen 1.16b (Firefox 143.0.1) (64-bit)",
  "assets": {
    "zen-dense-tabs.css": ":root {\n    --dense-zen-workspace-indicator-height: calc(var(--zen-workspace-indicator-height) * 0.8);\n    --dense-tab-min-height: calc(var(--tab-min-height) * 0.7);\n}\n\n.zen-current-workspace-indicator {\n    max-height: var(--dense-zen-workspace-indicator-height) !important;\n    min-height: var(--dense-zen-workspace-indicator-height) !important;\n}\n\n.tab-group-label-container {\n    min-height: var(--dense-tab-min-height) !important;\n    max-height: var(--dense-tab-min-height) !important;\n}\n\n.zen-essentials-container zen-workspace-tabs-section {\n    align-items: center;\n}\n\n.tabbrowser-tab .tab-content {\n    min-height: var(--dense-tab-min-height) !important;\n    max-height: var(--dense-tab-min-height) !important;\n    align-self: center !important;\n}\n\n.tabbrowser-tab .tab-icon-stack {\n    align-self: center !important;\n}\n\n.tab-group-label-container .tab-group-folder-icon {\n    display: flex;\n    align-self: center;\n}\n\n.tabbrowser-tab .tab-background {\n    min-height: var(--dense-tab-min-height) !important;\n    max-height: var(--dense-tab-min-height) !important;\n\n    display: flex !important;\n    align-items: center !important;\n}\n\n.toolbarbutton-text {\n    align-self: center !important;\n}\n\n#tabs-newtab-button, #vertical-tabs-newtab-button {\n    min-height: var(--dense-tab-min-height) !important;\n    max-height: var(--dense-tab-min-height) !important;\n    align-content: center !important;\n    align-items: center !important;\n    align-self: center !important;\n}\n"
  },
  "category": "appearance",
  "license": "MIT"
}